gnd/__init__.py
gnd/admin.py
gnd/apps.py
gnd/fields.py
gnd/forms.py
gnd/models.py
gnd/utils.py
gnd/views.py
gnd/widgets.py
gnd/static/gnd/lobid-ac.js
django_gnd-0.3.0.dist-info/LICENSE
django_gnd-0.3.0.dist-info/METADATA
django_gnd-0.3.0.dist-info/WHEEL
django_gnd-0.3.0.dist-info/top_level.txt
django_gnd-0.3.0.dist-info/RECORD
