Metadata-Version: 2.1
Name: django-gnd
Version: 0.3.0
Summary: A django package to query and store data from Lobid's GND-API
Home-page: https://github.com/acdh-oeaw/django-gnd
Author: Peter Andorfer
Author-email: peter.andorfer@oeaw.ac.at
License: MIT
Keywords: django-gnd
Platform: UNKNOWN
License-File: LICENSE
Requires-Dist: Django (>=3.1)
Requires-Dist: pylobid (>=1.3.1)
Requires-Dist: python-dateutil (>=2.8)
